introcs/__init__.py
introcs/colors.py
introcs/filetools.py
introcs/modlib.py
introcs/strings.py
introcs/testcase.py
introcs/tuples.py
introcs/urltools.py
introcs/geom/__init__.py
introcs/geom/matrix.py
introcs/geom/point.py
introcs/geom/tuple.py
introcs/geom/vector.py
introcs/turtle/__init__.py
introcs/turtle/__main__.py
introcs/turtle/_context.py
introcs/turtle/_drawtool.py
introcs/turtle/pentool.py
introcs/turtle/turtle.py
introcs/turtle/window.py
introcs-1.3.1.dist-info/LICENSE
introcs-1.3.1.dist-info/METADATA
introcs-1.3.1.dist-info/WHEEL
introcs-1.3.1.dist-info/top_level.txt
introcs-1.3.1.dist-info/RECORD
